Metadata-Version: 2.1
Name: pgsync-kaboom
Version: 2.5.0
Summary: Postgres to Elasticsearch/OpenSearch sync
Home-page: https://github.com/toluaina/pgsync
Author: Tolu Aina
Author-email: tolu@pgsync.com
Maintainer: Tolu Aina
Maintainer-email: tolu@pgsync.com
License: LGPLv3
Project-URL: Bug Reports, https://github.com/toluaina/pgsync/issues
Project-URL: Funding, https://github.com/sponsors/toluaina
Project-URL: Source, https://github.com/toluaina/pgsync
Project-URL: Web, https://pgsync.com
Project-URL: Documentation, https://pgsync.com
Keywords: pgsync,elasticsearch,opensearch,postgres,change data capture
Platform: UNKNOWN
Classifier: Development Status :: 5 - Production/Stable
Classifier: Intended Audience :: Developers
Classifier: Natural Language :: English
Classifier: Programming Language :: Python :: 3.7
Classifier: Programming Language :: Python :: 3.8
Classifier: Programming Language :: Python :: 3.9
Classifier: Programming Language :: Python :: 3.10
Classifier: Programming Language :: Python :: 3.11
Classifier: Programming Language :: Python :: Implementation :: CPython
Classifier: Programming Language :: Python :: Implementation :: PyPy
Classifier: License :: OSI Approved :: GNU Lesser General Public License v3 (LGPLv3)
Requires-Python: >=3.7.0
License-File: LICENSE
License-File: AUTHORS.rst
Requires-Dist: async-timeout==4.0.2
Requires-Dist: black==22.12.0
Requires-Dist: boto3==1.26.59
Requires-Dist: botocore==1.29.59
Requires-Dist: bump2version==1.0.1
Requires-Dist: bumpversion==0.6.0
Requires-Dist: certifi==2022.12.7
Requires-Dist: charset-normalizer==3.0.1
Requires-Dist: click==8.1.3
Requires-Dist: distlib==0.3.6
Requires-Dist: elasticsearch==7.13.4
Requires-Dist: elasticsearch-dsl==7.4.0
Requires-Dist: environs==9.5.0
Requires-Dist: faker==16.6.1
Requires-Dist: filelock==3.9.0
Requires-Dist: greenlet==2.0.2
Requires-Dist: idna==3.4
Requires-Dist: importlib-metadata==4.2.0
Requires-Dist: isort==5.11.4
Requires-Dist: jmespath==1.0.1
Requires-Dist: marshmallow==3.19.0
Requires-Dist: mypy-extensions==0.4.3
Requires-Dist: newrelic==8.5.0
Requires-Dist: opensearch-dsl==2.0.1
Requires-Dist: opensearch-py==2.1.1
Requires-Dist: packaging==23.0
Requires-Dist: pathspec==0.11.0
Requires-Dist: platformdirs==2.6.2
Requires-Dist: psycopg2-binary==2.9.5
Requires-Dist: python-dateutil==2.8.2
Requires-Dist: python-dotenv==0.21.1
Requires-Dist: redis==4.4.2
Requires-Dist: requests==2.28.2
Requires-Dist: requests-aws4auth==1.2.1
Requires-Dist: s3transfer==0.6.0
Requires-Dist: six==1.16.0
Requires-Dist: sqlalchemy==1.4.46
Requires-Dist: sqlparse==0.4.3
Requires-Dist: tomli==2.0.1
Requires-Dist: typing-extensions==4.4.0
Requires-Dist: urllib3==1.26.14
Requires-Dist: virtualenv==20.16.2
Requires-Dist: zipp==3.12.0
